lazy/__init__.py
lazy/api/__init__.py
lazy/api/backends.py
lazy/api/base_imports.py
lazy/api/client.py
lazy/api/config.py
lazy/api/fast.py
lazy/api/timez.py
lazy/api/types.py
lazy/api/utils.py
lazy/cli/__init__.py
lazy/cli/apps/__init__.py
lazy/cli/apps/base.py
lazy/cli/apps/serialize_app.py
lazy/cmd/__init__.py
lazy/cmd/_examples.py
lazy/cmd/auto.py
lazy/cmd/base.py
lazy/cmd/contrib.py
lazy/cmd/core.py
lazy/cmd/exceptions.py
lazy/cmd/utils.py
lazy/configz/__init__.py
lazy/configz/cloudz.py
lazy/configz/common.py
lazy/configz/core.py
lazy/configz/types.py
lazy/httpz/__init__.py
lazy/httpz/reqz.py
lazy/io/__init__.py
lazy/io/cachez/__init__.py
lazy/io/cachez/_json.py
lazy/io/cachez/base.py
lazy/io/cachez/config.py
lazy/io/cachez/core_v1.py
lazy/io/cachez/extensions.py
lazy/io/cachez/persistent.py
lazy/io/cachez/static.py
lazy/io/cachez/static_v1.py
lazy/io/fuze_v1/__init__.py
lazy/io/fuze_v1/core.py
lazy/io/fuze_v2/__init__.py
lazy/io/fuze_v2/cloud.py
lazy/io/fuze_v2/core.py
lazy/io/fuze_v2/generic.py
lazy/io/fuze_v2/manager.py
lazy/io/fuze_v2/ops.py
lazy/io/fuze_v2/opsfuze.py
lazy/io/fuze_v2/utils.py
lazy/io/pathz/__init__.py
lazy/io/pathz/_base.py
lazy/io/pathz/_cloud.py
lazy/io/pathz/_cloud_static.py
lazy/io/pathz/_flavours.py
lazy/io/pathz/base.py
lazy/io/pathz/cloud.py
lazy/io/pathz/core.py
lazy/io/pathz/generic.py
lazy/io/pathz/types.py
lazy/io/pathz_v2/__init__.py
lazy/io/pathz_v2/base.py
lazy/io/pathz_v2/base_imports.py
lazy/io/pathz_v2/baselib.py
lazy/io/pathz_v2/flavours.py
lazy/io/pathz_v2/generic.py
lazy/io/pathz_v2/pathlibz.py
lazy/io/pathz_v2/types.py
lazy/io/pathz_v2/aiopathz/__init__.py
lazy/io/pathz_v2/aiopathz/handle.py
lazy/io/pathz_v2/aiopathz/scandir.py
lazy/io/pathz_v2/aiopathz/selectors.py
lazy/io/pathz_v2/aiopathz/types.py
lazy/io/pathz_v2/aiopathz/wrap.py
lazy/io/pathz_v2/providers/__init__.py
lazy/io/pathz_v2/providers/base.py
lazy/io/pathz_v2/providers/cfs_base.py
lazy/io/pathz_v2/providers/cfs_pathz_base.py
lazycls-0.1.15.dist-info/LICENSE
lazycls-0.1.15.dist-info/METADATA
lazycls-0.1.15.dist-info/WHEEL
lazycls-0.1.15.dist-info/entry_points.txt
lazycls-0.1.15.dist-info/top_level.txt
lazycls-0.1.15.dist-info/RECORD
