Metadata-Version: 2.1
Name: lazycls
Version: 0.1.15
Summary: Python Utilities for the Super Lazy
Home-page: https://github.com/trisongz/lazycls
Author: Tri Songz
Author-email: ts@growthengineai.com
License: MIT Style
Classifier: Intended Audience :: Developers
Classifier: License :: OSI Approved :: MIT License
Classifier: Programming Language :: Python :: 3.7
Classifier: Topic :: Software Development :: Libraries
License-File: LICENSE
Requires-Dist: anyio
Requires-Dist: aiofile
Requires-Dist: dill
Requires-Dist: fsspec
Requires-Dist: orjson
Requires-Dist: pydantic[dotenv]
Requires-Dist: pylogz
Requires-Dist: pysimdjson
Requires-Dist: pyyaml
Requires-Dist: sniffio
Requires-Dist: typer
Requires-Dist: universal-pathlib
Requires-Dist: PyJWT
Provides-Extra: cloudfs
Requires-Dist: gcsfs ; extra == 'cloudfs'
Requires-Dist: s3fs ; extra == 'cloudfs'
Provides-Extra: gcs
Requires-Dist: gcsfs ; extra == 'gcs'
Provides-Extra: s3
Requires-Dist: s3fs ; extra == 's3'
